langchain_jupyter/__init__.py
langchain_jupyter/__version__.py
langchain_jupyter/tests/__init__.py
langchain_jupyter-0.1.0.dist-info/METADATA
langchain_jupyter-0.1.0.dist-info/WHEEL
langchain_jupyter-0.1.0.dist-info/entry_points.txt
langchain_jupyter-0.1.0.dist-info/licenses/LICENSE
langchain_jupyter-0.1.0.dist-info/RECORD
