Metadata-Version: 2.4
Name: langchain_jupyter
Version: 0.1.0
Project-URL: Home, https://github.com/datalayer/langchain-jupyter
Author-email: Datalayer <info@datalayer.io>
License: BSD 3-Clause License
License-File: LICENSE
Keywords: Jupyter
Classifier: Intended Audience :: Developers
Classifier: Intended Audience :: System Administrators
Classifier: License :: OSI Approved :: BSD License
Classifier: Programming Language :: Python
Classifier: Programming Language :: Python :: 3
Requires-Python: >=3.9
Requires-Dist: jupyter-kernel-client
Requires-Dist: jupyter-nbmodel-client
Requires-Dist: langchain
Requires-Dist: langchain-openai
Requires-Dist: python-dotenv
Provides-Extra: example
Requires-Dist: jupyter-server-ydoc; extra == 'example'
Provides-Extra: lint
Requires-Dist: mdformat-gfm>=0.3.5; extra == 'lint'
Requires-Dist: mdformat>0.7; extra == 'lint'
Requires-Dist: ruff; extra == 'lint'
Provides-Extra: test
Requires-Dist: ipykernel; extra == 'test'
Requires-Dist: jupyter-server<3,>=1.6; extra == 'test'
Requires-Dist: pytest>=7.0; extra == 'test'
Provides-Extra: typing
Requires-Dist: mypy>=0.990; extra == 'typing'
